{
  "arquivo_pdf": "/app/pnad/pnadc_202404_trimestre_quadroSintetico.pdf",
  "periodo": "out-nov-dez/2024",
  "geografias": [
    "Brasil",
    "Nordeste",
    "Maranhão",
    "Piauí",
    "Ceará",
    "Rio Grande do Norte",
    "Paraíba",
    "Pernambuco",
    "Alagoas",
    "Sergipe",
    "Bahia"
  ],
  "linhas_csv": 99,
  "regioes_macro": {
    "Norte": {
      "Taxa de desocupação": 6.9,
      "Nível da ocupação": 56.7,
      "Taxa de participação na força de trabalho": 60.9,
      "Ocupadas": 8479.0,
      "Desocupadas": 624.0,
      "Pessoas de 14 anos ou mais": 14950.0,
      "Taxa composta de subutilização da força de trabalho": 17.5,
      "Rendimento médio mensal real habitual": 2557.0,
      "Massa de rendimento mensal real habitual": 20800.0
    },
    "Nordeste": {
      "Taxa de desocupação": 8.6,
      "Nível da ocupação": 50.4,
      "Taxa de participação na força de trabalho": 55.2,
      "Ocupadas": 23626.0,
      "Desocupadas": 2230.0,
      "Pessoas de 14 anos ou mais": 46871.0,
      "Taxa composta de subutilização da força de trabalho": 25.5,
      "Rendimento médio mensal real habitual": 2284.0,
      "Massa de rendimento mensal real habitual": 52943.0
    },
    "Centro-Oeste": {
      "Taxa de desocupação": 5.0,
      "Nível da ocupação": 64.2,
      "Taxa de participação na força de trabalho": 67.5,
      "Ocupadas": 8819.0,
      "Desocupadas": 459.0,
      "Pessoas de 14 anos ou mais": 13739.0,
      "Taxa composta de subutilização da força de trabalho": 11.1,
      "Rendimento médio mensal real habitual": 3796.0,
      "Massa de rendimento mensal real habitual": 33230.0
    },
    "Sudeste": {
      "Taxa de desocupação": 5.9,
      "Nível da ocupação": 61.4,
      "Taxa de participação na força de trabalho": 65.2,
      "Ocupadas": 46535.0,
      "Desocupadas": 2901.0,
      "Pessoas de 14 anos ou mais": 75839.0,
      "Taxa composta de subutilização da força de trabalho": 12.3,
      "Rendimento médio mensal real habitual": 3738.0,
      "Massa de rendimento mensal real habitual": 172700.0
    },
    "Sul": {
      "Taxa de desocupação": 3.6,
      "Nível da ocupação": 64.4,
      "Taxa de participação na força de trabalho": 66.8,
      "Ocupadas": 16359.0,
      "Desocupadas": 608.0,
      "Pessoas de 14 anos ou mais": 25412.0,
      "Taxa composta de subutilização da força de trabalho": 7.8,
      "Rendimento médio mensal real habitual": 3704.0,
      "Massa de rendimento mensal real habitual": 59778.0
    }
  },
  "brasil_agregado": {
    "Taxa de desocupação": 6.165943600867679,
    "Nível da ocupação": 58.716935032322645,
    "Taxa de participação na força de trabalho": 62.575292261228086,
    "Ocupadas": 103818.0,
    "Desocupadas": 6822.0,
    "Pessoas de 14 anos ou mais": 176811.0,
    "Rendimento médio mensal real habitual": 3310.226328767651,
    "Massa de rendimento mensal real habitual": 339451.0,
    "Taxa composta de subutilização da força de trabalho": 15.498875635565662
  }
}